{"is_source_file": true, "format": "JavaScript (React)", "description": "This is a React frontend entry point that sets up routing for a web application, including protected routes and login handling.", "external_files": ["./index.css", "./context/AuthContext", "./components/ProtectedRoute", "./pages/Login", "./pages/Dashboard"], "external_methods": ["ReactDOM.createRoot", "React.StrictMode", "ReactDOM.createRoot", "React.createElement"], "published": ["React", "ReactDOM", "AuthProvider", "ProtectedRoute", "Login", "Dashboard"], "classes": [], "methods": [{"name": "root.render", "description": "Initializes rendering of the React app within the root DOM element."}], "calls": ["ReactDOM.createRoot", "root.render", "React.StrictMode", "AuthProvider", "BrowserRouter", "Routes", "Route", "Navigate", "ProtectedRoute", "Login", "Dashboard"], "search-terms": ["ReactDOM", "Routing", "ProtectedRoute", "Login", "React", "createRoot", "index.js", "Frontend entry point"], "state": 2, "file_id": 20, "knowledge_revision": 35, "git_revision": "8bbb0411bb70dd520a6191d0c63ebafa49710cce", "revision_history": [{"24": "8bbb0411bb70dd520a6191d0c63ebafa49710cce"}, {"35": "8bbb0411bb70dd520a6191d0c63ebafa49710cce"}], "ctags": [{"_type": "tag", "name": "root", "path": "/home/kavia/workspace/code-generation/timetrack-pro-199350-199363/chronose_frontend/src/index.js", "pattern": "/^const root = ReactDOM.createRoot(document.getElementById('root'));$/", "language": "JavaScript", "kind": "constant"}], "hash": "7a7767db20373ec00f8981bb0f9940ae", "format-version": 4, "code-base-name": "chronose_frontend", "filename": "chronose_frontend/src/index.js"}