{"is_source_file": true, "format": "JavaScript", "description": "This file is a Vite configuration script for a React project, defining build and development server settings.", "external_files": ["node_modules/@vitejs/plugin-react", "path"], "external_methods": ["defineConfig", "loadEnv"], "published": ["default"], "classes": [], "methods": [{"name": "defineConfig", "description": "Defines the Vite configuration object, potentially with environment-specific settings."}, {"name": "loadEnv", "description": "Loads environment variables based on the current mode from the process working directory."}], "calls": ["defineConfig", "loadEnv", "react()", "path.resolve"], "search-terms": ["vite.config.js", "Vite configuration", "React plugin", "loadEnv", "defineConfig", "build server settings"], "state": 2, "file_id": 3, "knowledge_revision": 12, "git_revision": "", "ctags": [], "hash": "6c2023aa696e99dcd76a17fd1efc8934", "format-version": 4, "code-base-name": "chronose_frontend", "filename": "chronose_frontend/vite.config.js", "revision_history": [{"12": ""}]}